{
  "generated_at": "2026-03-29T00:38:19.590090+08:00",
  "total_titles_processed": 315,
  "failed_sources": [],
  "trends": [
    {
      "keyword_group": "NBA2K NBA2KON2 球员数据更新 2Kratings NBA周最佳 NBA月最佳 shams Ronnie2K NBA交易 特朗普",
      "match_count": 8,
      "titles": [
        {
          "title": "特朗普发出威胁：“下一个是古巴”",
          "url": "https://www.cls.cn/detail/2327781",
          "source": "财联社热门",
          "ranks": [
            1
          ],
          "is_new": false,
          "appearance_count": 1,
          "time_info": "00时38分"
        },
        {
          "title": "特朗普吹嘘：中国又下单大豆了，老乡快买拖拉机",
          "url": "https://news.ifeng.com/c/8rr9Q5dkmnZ",
          "source": "凤凰网",
          "ranks": [
            3
          ],
          "is_new": false,
          "appearance_count": 1,
          "time_info": "00时38分"
        },
        {
          "title": "特朗普“口头缓和”失效，原油“现货冲击”逼近，美股真的慌了！",
          "url": "https://wallstreetcn.com/articles/3768633",
          "source": "华尔街见闻",
          "ranks": [
            4
          ],
          "is_new": false,
          "appearance_count": 1,
          "time_info": "00时38分"
        },
        {
          "title": "想跑跑不了，特朗普失控",
          "url": "https://news.ifeng.com/c/8rrd4miP6TY",
          "source": "凤凰网",
          "ranks": [
            6
          ],
          "is_new": false,
          "appearance_count": 1,
          "time_info": "00时38分"
        },
        {
          "title": "特朗普总在周末出手，华尔街已经不敢持仓过周末了",
          "url": "https://wallstreetcn.com/articles/3768631",
          "source": "华尔街见闻",
          "ranks": [
            7
          ],
          "is_new": false,
          "appearance_count": 1,
          "time_info": "00时38分"
        },
        {
          "title": "特朗普谈中国：对中国的成就必须非常尊重",
          "url": "https://m.thepaper.cn/newsDetail_forward_32849114",
          "source": "澎湃新闻",
          "ranks": [
            11
          ],
          "is_new": false,
          "appearance_count": 1,
          "time_info": "00时38分"
        },
        {
          "title": "“末日博士”鲁比尼：特朗普更有可能升级伊朗局势而非选择退让",
          "url": "https://www.cls.cn/detail/2327594",
          "source": "财联社热门",
          "ranks": [
            12
          ],
          "is_new": false,
          "appearance_count": 1,
          "time_info": "00时38分"
        },
        {
          "title": "泽连斯基：我希望特朗普不会忘记乌克兰冲突。",
          "url": "https://wallstreetcn.com/livenews/3078609",
          "source": "华尔街见闻-快讯",
          "ranks": [
            22
          ],
          "is_new": false,
          "appearance_count": 1,
          "time_info": "00时38分"
        }
      ]
    }
  ],
  "report_image_url": "https://github.com/rea1akon/TrendRadar222k/img/news.jpg"
}